ucdmcmc/__init__.py
ucdmcmc/core.py
ucdmcmc/__pycache__/__init__.cpython-312.pyc
ucdmcmc/__pycache__/core.cpython-312.pyc
ucdmcmc/models/models_atmo20pp_JWST-NIRSPEC-PRISM.h5
ucdmcmc/models/models_atmo20pp_SPEX-PRISM.h5
ucdmcmc/models/models_btsettl08_JWST-NIRSPEC-PRISM.h5
ucdmcmc/models/models_btsettl08_SPEX-PRISM.h5
ucdmcmc/models/models_dback24_JWST-NIRSPEC-PRISM.h5
ucdmcmc/models/models_dback24_SPEX-PRISM.h5
ucdmcmc/models/models_karalidi21_JWST-NIRSPEC-PRISM.h5
ucdmcmc/models/models_karalidi21_SPEX-PRISM.h5
ucdmcmc/models/models_lacy23_JWST-NIRSPEC-PRISM.h5
ucdmcmc/models/models_lacy23_SPEX-PRISM.h5
ucdmcmc/models/wave_EUCLID-old.csv
ucdmcmc/models/wave_EUCLID.csv
ucdmcmc/models/wave_FIRE-ECHELLE.csv
ucdmcmc/models/wave_FIRE-PRISM.csv
ucdmcmc/models/wave_JWST-MIRI-LRS.csv
ucdmcmc/models/wave_JWST-NIRSPEC-G395H-old.csv
ucdmcmc/models/wave_JWST-NIRSPEC-G395H.csv
ucdmcmc/models/wave_JWST-NIRSPEC-MIRI.csv
ucdmcmc/models/wave_JWST-NIRSPEC-PRISM.csv
ucdmcmc/models/wave_KECK-NIRES.csv
ucdmcmc/models/wave_NIR.csv
ucdmcmc/models/wave_OIR.csv
ucdmcmc/models/wave_SPEX-PRISM.csv
ucdmcmc/models/wave_SPEX-SXD.csv
ucdmcmc/models/wave_STIS-SXD.csv
ucdmcmc/opacities/exomol/12C-16O2_1500-5000_350K_0.400000.sigma
ucdmcmc/opacities/exomol/12C-16O2_500-12000_600K_0.250000.sigma
ucdmcmc/opacities/exomol/12C-16O2_500-12000_600K_1.000000.sigma
ucdmcmc/opacities/exomol/12C-16O_1500-5000_350K_0.400000.sigma
ucdmcmc/opacities/exomol/12C-16O_500-12000_3400K_0.200000.sigma
ucdmcmc/opacities/exomol/12C-16O_500-12000_600K_0.250000.sigma
ucdmcmc/opacities/exomol/12C-16O_500-12000_600K_1.000000.sigma
ucdmcmc/opacities/exomol/12C-1H4_1500-5000_350K_0.400000.sigma
ucdmcmc/opacities/exomol/12C-1H4_1500-5000_500K_0.400000.sigma
ucdmcmc/opacities/exomol/12C-1H4_500-11999_600K_0.250000.sigma
ucdmcmc/opacities/exomol/12C-1H4_500-11999_600K_1.000000.sigma
ucdmcmc/opacities/exomol/14N-1H3_1500-5000_350K_0.400000.sigma
ucdmcmc/opacities/exomol/14N-1H3_500-11999_600K_0.250000.sigma
ucdmcmc-1.4.dist-info/licenses/LICENSE
ucdmcmc-1.4.dist-info/METADATA
ucdmcmc-1.4.dist-info/WHEEL
ucdmcmc-1.4.dist-info/top_level.txt
ucdmcmc-1.4.dist-info/RECORD
