Metadata-Version: 2.4
Name: ucdmcmc
Version: 1.4
Summary: MCMC fitting code for low temperature atmosphere spectra
Author-email: Adam Burgasser <aburgasser@ucsd.edu>
Maintainer-email: Adam Burgasser <aburgasser@ucsd.edu>
Project-URL: Repository, https://github.com/aburgasser/ucdmcmc.git
Project-URL: Issues, https://github.com/aburgasser/ucdmcmc/issues
Classifier: Development Status :: 4 - Beta
Classifier: Programming Language :: Python :: 3.10
Classifier: Programming Language :: Python :: 3.11
Classifier: Programming Language :: Python :: 3.12
Classifier: Programming Language :: Python :: 3.13
Requires-Python: >=3.10
License-File: LICENSE
Requires-Dist: astropy
Requires-Dist: astroquery
Requires-Dist: corner
Requires-Dist: emcee
Requires-Dist: matplotlib
Requires-Dist: numpy<2.0
Requires-Dist: pandas
Requires-Dist: tables
Requires-Dist: requests
Requires-Dist: scipy
Requires-Dist: spectres
Requires-Dist: splat
Requires-Dist: statsmodels
Requires-Dist: tqdm
Requires-Dist: importlib_resources; python_version < "3.7"
Provides-Extra: test
Requires-Dist: pytest; extra == "test"
Requires-Dist: ruff; extra == "test"
Dynamic: license-file
